pyden/__init__.py
pyden/__version__.py
pyden/client.py
pyden/errors.py
pyden/trash.py
pyden-1.0.4.dist-info/METADATA
pyden-1.0.4.dist-info/RECORD
pyden-1.0.4.dist-info/WHEEL
pyden-1.0.4.dist-info/top_level.txt
