Metadata-Version: 2.1
Name: pyden
Version: 1.0.4
Summary: A Python API for info from the City and County of Denver, CO
Home-page: https://github.com/bachya/pyden
Author: Aaron Bach
Author-email: bachya1208@gmail.com
License: MIT
Platform: UNKNOWN
Classifier: License :: OSI Approved :: MIT License
Classifier: Programming Language :: Python
Classifier: Programming Language :: Python :: 3
Classifier: Programming Language :: Python :: 3.5
Classifier: Programming Language :: Python :: 3.6
Classifier: Programming Language :: Python :: 3.7
Classifier: Programming Language :: Python :: Implementation :: CPython
Classifier: Programming Language :: Python :: Implementation :: PyPy
Requires-Python: >=3.5.3
Requires-Dist: aiocache
Requires-Dist: aiodns
Requires-Dist: aiohttp
Requires-Dist: async-timeout
Requires-Dist: geocoder
Requires-Dist: ics
Requires-Dist: msgpack
Requires-Dist: pytz
Requires-Dist: ujson
